PACKAGE_DJANGO/__init__.py
PACKAGE_DJANGO/__main__.py
PACKAGE_DJANGO/gen.py
create_django-0.0.4.dist-info/METADATA
create_django-0.0.4.dist-info/WHEEL
create_django-0.0.4.dist-info/entry_points.txt
create_django-0.0.4.dist-info/top_level.txt
create_django-0.0.4.dist-info/RECORD
