Metadata-Version: 2.4
Name: create_django
Version: 0.0.4
Summary: Un utilitaire pour créer rapidement une structure d'app Django avec des templates de base.
Author: Tieba
Author-email: Meite <metetieba@gmail.com>
Requires-Python: >=3.6
Dynamic: author
Dynamic: requires-python
